ColorController/__init__.py
ColorController/ColorController.py
ColorController/colornames.txt
ColorController/conversions.py
ColorController/helpers.py
ColorController/LICENSE
ColorController/namelookup.py
ColorController/readmepics/bright_aqua.PNG
ColorController/readmepics/chartreuse.PNG
ColorController/readmepics/cocoa.PNG
ColorController/readmepics/crimson_red.PNG
ColorController/readmepics/crimson_red2.PNG
ColorController/readmepics/deep_orchid.PNG
ColorController/readmepics/forest.PNG
ColorController/readmepics/grape.PNG
ColorController/readmepics/grayish_fuchsia.PNG
ColorController/readmepics/hunter_green.PNG
ColorController/readmepics/mint.PNG
ColorController/readmepics/nutmeg.PNG
ColorController/readmepics/pale_orchid.PNG
ColorController/show_color.py
ColorController/test_conversions.py
ColorController/test_namelookup.py
colorcontroller-0.1.9.dist-info/WHEEL
colorcontroller-0.1.9.dist-info/METADATA
colorcontroller-0.1.9.dist-info/RECORD
