Metadata-Version: 2.1
Name: colorcontroller
Version: 0.1.9
Summary: ColorController is a Pythonic interface for managing colors using either english-language names or one of several standard color values.
Home-page: https://github.com/tal-z/ColorController
License: MIT
Author: Tal Zaken
Author-email: talzaken@gmail.com
Requires-Python: >=3.9,<3.11
Classifier: License :: OSI Approved :: MIT License
Classifier: Programming Language :: Python :: 3
Classifier: Programming Language :: Python :: 3.10
Classifier: Programming Language :: Python :: 3.9
Requires-Dist: Pillow (>=8.4.0,<9.0.0)
Requires-Dist: cycler (>=0.11.0,<0.12.0)
Requires-Dist: fonttools (>=4.28.3,<5.0.0)
Requires-Dist: kiwisolver (>=1.3.2,<2.0.0)
Requires-Dist: matplotlib (>=3.5.0,<4.0.0)
Requires-Dist: numpy (>=1.21.4,<2.0.0)
Requires-Dist: packaging (>=21.3,<22.0)
Requires-Dist: pandas (>=1.3.4,<2.0.0)
Requires-Dist: pyparsing (>=3.0.6,<4.0.0)
Requires-Dist: python-dateutil (>=2.8.2,<3.0.0)
Requires-Dist: pytz (>=2021.3,<2022.0)
Requires-Dist: setuptools-scm (>=6.3.2,<7.0.0)
Requires-Dist: six (>=1.16.0,<2.0.0)
Requires-Dist: tomli (>=1.2.2,<2.0.0)
Project-URL: Repository, https://github.com/tal-z/ColorController
